nuha/__init__.py
nuha/cli/__init__.py
nuha/cli/main.py
nuha/cli/commands/__init__.py
nuha/cli/commands/analyze.py
nuha/cli/commands/config.py
nuha/cli/commands/debug.py
nuha/cli/commands/explain.py
nuha/cli/commands/setup.py
nuha/cli/commands/watch/__init__.py
nuha/cli/commands/watch/cli.py
nuha/cli/commands/watch/core.py
nuha/cli/commands/watch/display.py
nuha/cli/commands/watch/hooks.py
nuha/cli/commands/watch/monitor.py
nuha/core/__init__.py
nuha/core/ai_client.py
nuha/core/capture.py
nuha/core/command_parser.py
nuha/core/config.py
nuha/core/terminal_reader.py
nuha/utils/__init__.py
nuha/utils/formatter.py
nuha-1.0.0.dist-info/METADATA
nuha-1.0.0.dist-info/WHEEL
nuha-1.0.0.dist-info/entry_points.txt
nuha-1.0.0.dist-info/licenses/LICENSE
nuha-1.0.0.dist-info/RECORD
