Metadata-Version: 2.4
Name: nuha
Version: 1.0.0
Summary: AI-Powered Terminal Assistant That Understands Your Commands
Project-URL: Homepage, https://github.com/u3n-ai/nuha
Project-URL: Documentation, https://docs.nuha.ai
Project-URL: Repository, https://github.com/u3n-ai/nuha
Project-URL: Issues, https://github.com/u3n-ai/nuha/issues
Author-email: Nuha Team <support@nuha.ai>
License: MIT
License-File: LICENSE
Keywords: ai,assistant,automation,cli,terminal
Classifier: Development Status :: 4 - Beta
Classifier: Intended Audience :: Developers
Classifier: License :: OSI Approved :: MIT License
Classifier: Programming Language :: Python :: 3
Classifier: Programming Language :: Python :: 3.11
Classifier: Programming Language :: Python :: 3.12
Requires-Python: >=3.11
Requires-Dist: anthropic>=0.25.0
Requires-Dist: cryptography>=41.0.0
Requires-Dist: httpx>=0.25.0
Requires-Dist: openai>=1.0.0
Requires-Dist: psutil>=5.9.0
Requires-Dist: pydantic-settings>=2.0.0
Requires-Dist: pydantic>=2.0.0
Requires-Dist: rich>=13.0.0
Requires-Dist: toml>=0.10.2
Requires-Dist: typer>=0.9.0
Requires-Dist: zhipuai>=2.0.0
Provides-Extra: dev
Requires-Dist: pyrefly>=0.37.0; extra == 'dev'
Requires-Dist: pytest-asyncio>=0.21.0; extra == 'dev'
Requires-Dist: pytest-cov>=4.1.0; extra == 'dev'
Requires-Dist: pytest>=7.4.0; extra == 'dev'
Requires-Dist: ruff>=0.14.1; extra == 'dev'
Requires-Dist: types-toml>=0.10.8; extra == 'dev'
